cairo_parser/__init__.py
cairo_parser/__main__.py
cairo_parser/parser.py
cairo_parser/analysis/__init__.py
cairo_parser/analysis/analyzer.py
cairo_parser/analysis/cfg.py
cairo_parser/analysis/dataflow.py
cairo_parser/analysis/serialization.py
cairo_parser/analysis/statements.py
cairo_parser-0.2.0.dist-info/licenses/LICENSE
cairo_parser-0.2.0.dist-info/METADATA
cairo_parser-0.2.0.dist-info/WHEEL
cairo_parser-0.2.0.dist-info/entry_points.txt
cairo_parser-0.2.0.dist-info/top_level.txt
cairo_parser-0.2.0.dist-info/RECORD
