Metadata-Version: 2.4
Name: cairo-parser
Version: 0.2.0
Summary: Cairo smart contract parser with assembler-style GOT/PLT symbol resolution
Author-email: Calvin Kimani <calvinkimani475@gmail.com>
License-Expression: GPL-3.0-only
Project-URL: Homepage, https://github.com/raptor-audit/cairo-parser
Project-URL: Repository, https://github.com/raptor-audit/cairo-parser
Project-URL: Issues, https://github.com/raptor-audit/cairo-parser/issues
Keywords: cairo,starknet,parser,smart-contracts,blockchain,security,audit
Classifier: Development Status :: 4 - Beta
Classifier: Intended Audience :: Developers
Classifier: Topic :: Software Development :: Code Generators
Classifier: Topic :: Software Development :: Compilers
Classifier: Topic :: Security
Classifier: Programming Language :: Python :: 3
Classifier: Programming Language :: Python :: 3.8
Classifier: Programming Language :: Python :: 3.9
Classifier: Programming Language :: Python :: 3.10
Classifier: Programming Language :: Python :: 3.11
Classifier: Programming Language :: Python :: 3.12
Requires-Python: >=3.8
License-File: LICENSE
Provides-Extra: yaml
Requires-Dist: pyyaml; extra == "yaml"
Provides-Extra: dev
Requires-Dist: pytest; extra == "dev"
Requires-Dist: black; extra == "dev"
Requires-Dist: mypy; extra == "dev"
Dynamic: license-file
